mgcomtools/YcPgSimple.py
mgcomtools/YcPostgres.py
mgcomtools/YcSchema.py
mgcomtools/__init__.py
mgcomtools/gcp.py
mgcomtools/pgclass.py
mgcomtools/pgutils.py
mgcomtools/postgres.py
mgcomtools/schema.py
mgcomtools/tables.py
mgcomtools/telegram.py
mgcomtools/test.py
mgcomtools/tgclass.py
mgcomtools/yschema.py
mgcomtools-0.1.104.dist-info/METADATA
mgcomtools-0.1.104.dist-info/WHEEL
mgcomtools-0.1.104.dist-info/top_level.txt
mgcomtools-0.1.104.dist-info/RECORD
