Metadata-Version: 2.1
Name: mgcomtools
Version: 0.1.104
Summary: usefull tools for data-stories team.
Author: Mkozyrev (Maksim Kozyrev)
Author-email: <m.kozyrev@mgcom.ru>
Keywords: mgcom
Classifier: Development Status :: 1 - Planning
Classifier: Intended Audience :: Developers
Classifier: Programming Language :: Python :: 3
Classifier: Operating System :: Unix
Classifier: Operating System :: MacOS :: MacOS X
Classifier: Operating System :: Microsoft :: Windows
